ctrlstack/__init__.py
ctrlstack/cli.py
ctrlstack/controller.py
ctrlstack/controller_app.py
ctrlstack/remote_cli.py
ctrlstack/remote_controller.py
ctrlstack/server.py
ctrlstack-0.1.3.dist-info/METADATA
ctrlstack-0.1.3.dist-info/WHEEL
ctrlstack-0.1.3.dist-info/entry_points.txt
ctrlstack-0.1.3.dist-info/RECORD
