Metadata-Version: 2.4
Name: ctrlstack
Version: 0.1.3
Summary: Add your description here
Requires-Python: >=3.11
Requires-Dist: fastapi[standard]>=0.116.1
Requires-Dist: pandas>=2.3.0
Requires-Dist: pydantic>=2.11.5
Requires-Dist: python-dotenv>=1.1.0
Requires-Dist: rich>=14.0.0
Requires-Dist: typer>=0.16.0
